car/__init__.py
car/main.py
car/utils/__init__.py
car/utils/car_converge_control.py
car/utils/lambda_related_data_convert.py
car/utils/md_run_module.py
car/utils/analysis_module/FE_cal_convergence.py
car/utils/analysis_module/__init__.py
car/utils/analysis_module/plotting.py
car/utils/analysis_module/resample.py
car/utils/analysis_module/segment_analyse.py
car/utils/analysis_module/segment_related_tools.py
car/utils/input_parser/__init__.py
car/utils/input_parser/input_file_parser.py
car/utils/input_temp/__init__.py
car/utils/out_parser/__init__.py
car/utils/out_parser/re_func.py
car/utils/out_parser/read_amber_out.py
car/utils/out_parser/read_gmx_out.py
car/utils/out_parser/read_openmm_out.py
car_fep-1.1.1.dist-info/LICENSE
car_fep-1.1.1.dist-info/METADATA
car_fep-1.1.1.dist-info/WHEEL
car_fep-1.1.1.dist-info/entry_points.txt
car_fep-1.1.1.dist-info/top_level.txt
car_fep-1.1.1.dist-info/RECORD
